.gitignore
MANIFEST.in
Makefile
Procfile
README.md
out.csv
requirements.txt
setup.py
.github/workflows/pythonpackage.yml
tests/__init__.py
tests/exchange_test.py
toolbox502/__init__.py
toolbox502/exchange.py
toolbox502.egg-info/PKG-INFO
toolbox502.egg-info/SOURCES.txt
toolbox502.egg-info/dependency_links.txt
toolbox502.egg-info/not-zip-safe
toolbox502.egg-info/top_level.txt
toolbox502/data/countries_code.csv